{
  "coc.preferences.formatOnSaveFiletypes": [
    "css",
    "go",
    "graphql",
    "html",
    "javascript",
    "javascriptreact",
    "json",
    "jsonc",
    "markdown",
    "python",
    "rust",
    "typescript",
    "typescriptreact",
    "yaml"
  ],
  "coc.preferences.willSaveHandlerTimeout": 1000,
  "diagnostic.enableSign": true,
  "diagnostic.enableMessage": "always",
  "diagnostic.enableHighlightLineNumber": true,
  "diagnostic.checkCurrentLine": true,
  "diagnostic.messageTarget": "float",
  "diagnostic.errorSign": "✖",
  "diagnostic.warningSign": "⚠",
  "diagnostic-languageserver.filetypes": {
    "dockerfile": "hadolint",
    "sh": "shellcheck"
  },
  "eslint.filetypes": [
    "javascript",
    "javascriptreact",
    "typescript",
    "typescriptreact"
  ],
  "languageserver": {
    "bash": {
      "command": "bash-language-server",
      "args": ["start"],
      "filetypes": ["sh"],
      "ignoredRootPaths": ["~"]
    },
    "golang": {
      "command": "gopls",
      "rootPatterns": ["go.mod"],
      "filetypes": ["go"]
    },
    "terraform": {
      "command": "terraform-lsp",
      "filetypes": ["terraform"],
      "initializationOptions": {}
    }
  },
  "python.formatting.provider": "black",
  "python.linting.enabled": true,
  "python.linting.flake8Enabled": true,
  "python.linting.mypyEnabled": true,
  "python.sortImports.path": "isort"
}
